pytpro/__init__.py
pytpro/main.py
pytpro/markdown.py
pytpro/toasts.py
pytpro-0.2.9.dist-info/licenses/LICENSE
pytpro-0.2.9.dist-info/METADATA
pytpro-0.2.9.dist-info/WHEEL
pytpro-0.2.9.dist-info/top_level.txt
pytpro-0.2.9.dist-info/RECORD
