Metadata-Version: 2.4
Name: pytpro
Version: 0.2.9
Summary: A powerful Python toolkit with automatic HTML output and utilities by Ibrahim Akhlaq
Author: Ibrahim Akhlaq
Author-email: ibakhlaq@gmail.com
Keywords: python,tools,utilities,python tools,python utilities,math,random,utility,mathematics,randomness,random number,random numbers,random number generator,random number generators,random number generators python,html,css,javascript,markdown,markdown preview,markdown previewer,markdown previewer python
Classifier: Programming Language :: Python :: 3
Classifier: License :: OSI Approved :: MIT License
Classifier: Operating System :: OS Independent
Requires-Python: >=3.6
License-File: LICENSE
Requires-Dist: tkhtmlview
Dynamic: author
Dynamic: author-email
Dynamic: classifier
Dynamic: description
Dynamic: description-content-type
Dynamic: keywords
Dynamic: license-file
Dynamic: requires-dist
Dynamic: requires-python
Dynamic: summary
